README.rst
setup.py
sugargame2/__init__.py
sugargame2/canvas.py
sugargame2/event.py
sugargame2.egg-info/PKG-INFO
sugargame2.egg-info/SOURCES.txt
sugargame2.egg-info/dependency_links.txt
sugargame2.egg-info/requires.txt
sugargame2.egg-info/top_level.txt