Metadata-Version: 1.0
Name: sugargame2
Version: 0.1
Summary: A fork of sugargame, a module for using pygame in the Sugar toolkit
Home-page: https://github.com/platipy/sugargame2
Author: Platipy Project
Author-email: platipy@platipy.org
License: BSD
Keywords: pygame game engine sugar olpc
Platform: UNKNOWN
Classifier: Development Status :: 5 - Production/Stable
Classifier: Intended Audience :: Developers
Classifier: Intended Audience :: Education
Classifier: License :: OSI Approved :: BSD License
Classifier: Operating System :: POSIX :: Linux
Classifier: Programming Language :: Python :: 2 :: Only
Classifier: Topic :: Games/Entertainment
Classifier: Topic :: Multimedia
Classifier: Topic :: Software Development
Classifier: Topic :: Software Development :: Libraries :: pygame
